<?xml version="1.0" encoding="UTF-8" ?>

<cif>
	<chemical_name_common>Rutile</chemical_name_common>
	<chemical_formula_structural>TiO2</chemical_formula_structural>
	<space_group_IT_number>136</space_group_IT_number>
	<cell>
		<a unit="nm">0.45937</a>
		<b unit="nm">0.45937</b>
		<c unit="nm">0.29587</c>
		<alpha>90</alpha>
		<beta>90</beta>
		<gamma>90</gamma>
		<volume>0.0624347</volume>
	</cell>
	<atom_site>
		<label>Ti</label>
		<symbol>Ti</symbol>
		<fract_xyz>0 0 0</fract_xyz>
		<WyckoffSymbol>a</WyckoffSymbol>
	</atom_site>
	<atom_site>
		<label>O</label>
		<symbol>O</symbol>
		<fract_xyz>0.31 0.31 0</fract_xyz>
		<WyckoffSymbol>f</WyckoffSymbol>
	</atom_site>
</cif>
